{
  "Records": [
    {
      "messageId": "19dd0b57-b21e-4ac1-bd88-01bbb068cb78",
      "receiptHandle": "MessageReceiptHandle",
      "body": "140626483",
      "attributes": {
        "ApproximateReceiveCount": "120069738",
        "SentTimestamp": "1523232000000",
        "SenderId": "123456789012",
        "ApproximateFirstReceiveTimestamp": "1523232000001"
      },
      "messageAttributes": {},
      "md5OfBody": "{{{md5_of_body}}}",
      "eventSource": "aws:sqs",
      "eventSourceARN": "arn:aws:sqs:us-east-1:123456789012:MyQueue",
      "awsRegion": "us-east-1"
    },
    {
      "messageId": "19dd0b57-b21e-4ac1-bd88-01bbb068cb78",
      "receiptHandle": "MessageReceiptHandle",
      "body": "140626842",
      "attributes": {
        "ApproximateReceiveCount": "120069738",
        "SentTimestamp": "1523232000000",
        "SenderId": "123456789012",
        "ApproximateFirstReceiveTimestamp": "1523232000001"
      },
      "messageAttributes": {},
      "md5OfBody": "{{{md5_of_body}}}",
      "eventSource": "aws:sqs",
      "eventSourceARN": "arn:aws:sqs:us-east-1:123456789012:MyQueue",
      "awsRegion": "us-east-1"
    },
    {
      "messageId": "19dd0b57-b21e-4ac1-bd88-01bbb068cb78",
      "receiptHandle": "MessageReceiptHandle",
      "body": "140626428",
      "attributes": {
        "ApproximateReceiveCount": "120069738",
        "SentTimestamp": "1523232000000",
        "SenderId": "123456789012",
        "ApproximateFirstReceiveTimestamp": "1523232000001"
      },
      "messageAttributes": {},
      "md5OfBody": "{{{md5_of_body}}}",
      "eventSource": "aws:sqs",
      "eventSourceARN": "arn:aws:sqs:us-east-1:123456789012:MyQueue",
      "awsRegion": "us-east-1"
    },
    {
      "messageId": "19dd0b57-b21e-4ac1-bd88-01bbb068cb78",
      "receiptHandle": "MessageReceiptHandle",
      "body": "140626402",
      "attributes": {
        "ApproximateReceiveCount": "120069738",
        "SentTimestamp": "1523232000000",
        "SenderId": "123456789012",
        "ApproximateFirstReceiveTimestamp": "1523232000001"
      },
      "messageAttributes": {},
      "md5OfBody": "{{{md5_of_body}}}",
      "eventSource": "aws:sqs",
      "eventSourceARN": "arn:aws:sqs:us-east-1:123456789012:MyQueue",
      "awsRegion": "us-east-1"
    }
  ]
}